kmerpapa/CV_tools.py
kmerpapa/__init__.py
kmerpapa/__main__.py
kmerpapa/algorithms/all_kmers_CV.py
kmerpapa/algorithms/base.py
kmerpapa/algorithms/bottum_up_array_penalty_plus_pseudo_CV.py
kmerpapa/algorithms/bottum_up_array_w_numba.py
kmerpapa/algorithms/greedy_penalty_plus_pseudo.py
kmerpapa/cli.py
kmerpapa/io_utils.py
kmerpapa/papa.py
kmerpapa/pattern_utils.py
kmerpapa/score_utils.py
kmerpapa-0.2.4.dist-info/LICENSE
kmerpapa-0.2.4.dist-info/METADATA
kmerpapa-0.2.4.dist-info/WHEEL
kmerpapa-0.2.4.dist-info/entry_points.txt
kmerpapa-0.2.4.dist-info/RECORD
