Metadata-Version: 2.1
Name: kmerpapa
Version: 0.2.4
Summary: Tool to calculate a k-mer pattern partition from position specific k-mer counts.
Home-page: https://github.com/besenbacherLab/kmerpapa
License: MIT
Author: Søren Besenbacher
Author-email: besenbacher@clin.au.dk
Requires-Python: >=3.8,<3.11
Classifier: License :: OSI Approved :: MIT License
Classifier: Programming Language :: Python :: 3
Classifier: Programming Language :: Python :: 3.8
Classifier: Programming Language :: Python :: 3.9
Classifier: Programming Language :: Python :: 3.10
Requires-Dist: numba (>=0.56.2,<0.57.0)
Requires-Dist: numpy (>=1.23.3,<2.0.0)
Requires-Dist: scikit-optimize (>=0.9.0,<0.10.0)
Requires-Dist: scipy (>=1.9.1,<2.0.0)
Project-URL: Repository, https://github.com/besenbacherLab/kmerpapa
